gpcg/__init__.py
gpcg/examples.py
gpcg/gpcg.py
gpcg/util.py
gpcg-0.0.1.dist-info/LICENSE
gpcg-0.0.1.dist-info/METADATA
gpcg-0.0.1.dist-info/WHEEL
gpcg-0.0.1.dist-info/top_level.txt
gpcg-0.0.1.dist-info/RECORD
