Metadata-Version: 2.1
Name: gpcg
Version: 0.0.1
Summary: An implementation of a conjugate gradient algorithm (GPCG) for solving bound-constrained quadratic programs.
Author-email: Jonathan Lindbloom <jonathan@lindbloom.com>
Project-URL: Homepage, https://github.com/jlindbloom/gradient-projected-conjugate-gradient
Project-URL: Bug Tracker, https://github.com/jlindbloom/gradient-projected-conjugate-gradient/issues
Keywords: quadratic programming,conjugate gradient,bound constraints
Classifier: Programming Language :: Python :: 3
Classifier: License :: OSI Approved :: MIT License
Classifier: Operating System :: OS Independent
Classifier: Topic :: Scientific/Engineering :: Mathematics
Requires-Python: >=3.7
License-File: LICENSE
